MANIFEST.in
README.md
setup.py
coreapi_cli/__init__.py
coreapi_cli/auth.py
coreapi_cli/codec_plugins.py
coreapi_cli/compat.py
coreapi_cli/debug.py
coreapi_cli/display.py
coreapi_cli/history.py
coreapi_cli/main.py
coreapi_cli.egg-info/PKG-INFO
coreapi_cli.egg-info/SOURCES.txt
coreapi_cli.egg-info/dependency_links.txt
coreapi_cli.egg-info/entry_points.txt
coreapi_cli.egg-info/requires.txt
coreapi_cli.egg-info/top_level.txt