Metadata-Version: 1.1
Name: coreapi-cli
Version: 1.0.9
Summary: An interactive command line client for Core API.
Home-page: http://github.com/core-api/coreapi-cli/
Author: Tom Christie
Author-email: tom@tomchristie.com
License: BSD
Platform: UNKNOWN
Classifier: Intended Audience :: Developers
Classifier: License :: OSI Approved :: BSD License
Classifier: Operating System :: OS Independent
Classifier: Programming Language :: Python
Classifier: Programming Language :: Python :: 3
